.gitignore
CHANGELOG.md
MANIFEST.in
README.md
buildout.cfg
setup.cfg
setup.py
versions.cfg
src/waterbear/__init__.py
src/waterbear.service.cloudfront.egg-info/PKG-INFO
src/waterbear.service.cloudfront.egg-info/SOURCES.txt
src/waterbear.service.cloudfront.egg-info/dependency_links.txt
src/waterbear.service.cloudfront.egg-info/entry_points.txt
src/waterbear.service.cloudfront.egg-info/not-zip-safe
src/waterbear.service.cloudfront.egg-info/requires.txt
src/waterbear.service.cloudfront.egg-info/top_level.txt
src/waterbear/service/__init__.py
src/waterbear/service/cloudfront/__init__.py
src/waterbear/service/cloudfront/cloudfront.py
src/waterbear/service/cloudfront/test_cloudfront_lambda.py