Metadata-Version: 1.0
Name: waterbear.service.cloudfront
Version: 1.0.0
Summary: Waterbear Cloud Cloudfront service
Home-page: UNKNOWN
Author: UNKNOWN
Author-email: UNKNOWN
License: UNKNOWN
Platform: UNKNOWN
